deteksigempa/__init__.py
livrearthquakeindonesia-0.0.9.dist-info/LICENSE
livrearthquakeindonesia-0.0.9.dist-info/METADATA
livrearthquakeindonesia-0.0.9.dist-info/WHEEL
livrearthquakeindonesia-0.0.9.dist-info/entry_points.txt
livrearthquakeindonesia-0.0.9.dist-info/top_level.txt
livrearthquakeindonesia-0.0.9.dist-info/RECORD
