Metadata-Version: 2.1
Name: livrearthquakeindonesia
Version: 0.0.9
Summary: This package will get the latest earthquake form BMKG (Agency from Indonesia)
Home-page: https://github.com/gugunmfauzi/earthquake-detection-indonesia
Author: Gugun Muhammad Fauzi
Author-email: gugunmfauzi16@gmail.com
Classifier: Programming Language :: Python :: 3
Classifier: License :: OSI Approved :: GNU General Public License v3 or later (GPLv3+)
Classifier: Operating System :: OS Independent
Classifier: Development Status :: 4 - Beta
Requires-Python: >=3.6
License-File: LICENSE
Requires-Dist: numpy
Requires-Dist: pandas
